procesamiento/__init__.py
procesamiento/procesamiento_texto.py
procesadortext-1.0.dist-info/LICENSE
procesadortext-1.0.dist-info/METADATA
procesadortext-1.0.dist-info/WHEEL
procesadortext-1.0.dist-info/top_level.txt
procesadortext-1.0.dist-info/RECORD
