Metadata-Version: 2.1
Name: procesadortext
Version: 1.0
Summary: This is my text processor that will process text using 9 NLP processing tehcniques and two display
Home-page: 
Author: Carlos Estrada
Requires-Python: >=3.11
License-File: LICENSE
Requires-Dist: pandas ==2.1.4
Requires-Dist: pytest ==6.2.4
Requires-Dist: nltk ==3.6.5
Requires-Dist: setuptools ==69.0.2
Requires-Dist: jupyter ==1.0.0
Requires-Dist: matplotlib ==3.8.2
Requires-Dist: spacy ==3.7.2
Requires-Dist: wordcloud ==1.9.3
